FAMS/__init__.py
FAMS/model_rankings.py
FAMS/utils.py
FAMS-1.1.1.dist-info/LICENSE.md
FAMS-1.1.1.dist-info/METADATA
FAMS-1.1.1.dist-info/WHEEL
FAMS-1.1.1.dist-info/top_level.txt
FAMS-1.1.1.dist-info/RECORD
