Metadata-Version: 2.1
Name: FAMS
Version: 1.1.1
Summary: Fidelity Assessment for Model Selection
Author-email: Adam Cox <adam.cox@asdl.gatech.edu>
License: # GNU LESSER GENERAL PUBLIC LICENSE
Project-URL: Repository, https://github.com/awcox21/FAMS
Project-URL: Issues, https://github.com/awcox21/FAMS/issues
Requires-Python: >=3.5
License-File: LICENSE.md
Requires-Dist: tqdm
Requires-Dist: numpy
Requires-Dist: matplotlib
Requires-Dist: pandas
Requires-Dist: scipy
Requires-Dist: scikit-learn
Requires-Dist: adjustText
